logseq_mcp/__init__.py
logseq_mcp/mcp.py
logseq_mcp/client/__init__.py
logseq_mcp/client/logseq_client.py
logseq_mcp/tools/__init__.py
logseq_mcp/tools/blocks.py
logseq_mcp/tools/pages.py
logseq_mcp/utils/__init__.py
logseq_mcp/utils/logging.py
logseq_mcp-0.2.0.dist-info/METADATA
logseq_mcp-0.2.0.dist-info/WHEEL
logseq_mcp-0.2.0.dist-info/entry_points.txt
logseq_mcp-0.2.0.dist-info/RECORD
